{"cameraMode":{"drawMode":0,"name":"Shaded","section":"Shading Mode"},"sceneLighting":true,"audioPlay":false,"sceneViewState":{"showFog":true,"showMaterialUpdate":false,"showSkybox":true,"showFlares":true,"showImageEffects":true,"showParticleSystems":true},"in2DMode":false,"pivot":{"x":3.005129337310791,"y":5.61106014251709,"z":-13.734078407287598},"rotation":{"x":0.4066649079322815,"y":-0.010994615033268929,"z":0.004818960092961788,"w":0.9135514497756958},"size":16.64185905456543,"orthographic":false}